mock_spark/__init__.py
mock_spark/_version.py
mock_spark/config.py
mock_spark/delta.py
mock_spark/error_simulation.py
mock_spark/errors.py
mock_spark/performance_simulation.py
mock_spark/py.typed
mock_spark/spark_types.py
mock_spark/window.py
mock_spark/backend/__init__.py
mock_spark/backend/factory.py
mock_spark/backend/protocols.py
mock_spark/backend/polars/__init__.py
mock_spark/backend/polars/export.py
mock_spark/backend/polars/expression_translator.py
mock_spark/backend/polars/materializer.py
mock_spark/backend/polars/operation_executor.py
mock_spark/backend/polars/parquet_storage.py
mock_spark/backend/polars/schema_registry.py
mock_spark/backend/polars/schema_utils.py
mock_spark/backend/polars/storage.py
mock_spark/backend/polars/type_mapper.py
mock_spark/backend/polars/window_handler.py
mock_spark/compat/__init__.py
mock_spark/compat/datetime.py
mock_spark/core/__init__.py
mock_spark/core/condition_evaluator.py
mock_spark/core/data_validation.py
mock_spark/core/ddl_adapter.py
mock_spark/core/protocols.py
mock_spark/core/schema_inference.py
mock_spark/core/type_utils.py
mock_spark/core/exceptions/__init__.py
mock_spark/core/exceptions/analysis.py
mock_spark/core/exceptions/base.py
mock_spark/core/exceptions/execution.py
mock_spark/core/exceptions/operation.py
mock_spark/core/exceptions/py4j_compat.py
mock_spark/core/exceptions/runtime.py
mock_spark/core/exceptions/validation.py
mock_spark/core/interfaces/__init__.py
mock_spark/core/interfaces/dataframe.py
mock_spark/core/interfaces/functions.py
mock_spark/core/interfaces/session.py
mock_spark/core/interfaces/storage.py
mock_spark/core/types/__init__.py
mock_spark/core/types/data_types.py
mock_spark/core/types/metadata.py
mock_spark/core/types/schema.py
mock_spark/data_generation/__init__.py
mock_spark/data_generation/builder.py
mock_spark/data_generation/convenience.py
mock_spark/data_generation/generator.py
mock_spark/dataframe/__init__.py
mock_spark/dataframe/attribute_handler.py
mock_spark-3.14.0.dist-info/LICENSE
mock_spark-3.14.0.dist-info/METADATA
mock_spark-3.14.0.dist-info/WHEEL
mock_spark-3.14.0.dist-info/top_level.txt
mock_spark-3.14.0.dist-info/RECORD
