Metadata-Version: 2.1
Name: mock-spark
Version: 3.14.0
Summary: Lightning-fast PySpark testing without JVM - 10x faster with 100% API compatibility
Author-email: Odos Matthews <odosmatthews@gmail.com>
Maintainer-email: Odos Matthews <odosmatthews@gmail.com>
License: MIT
Project-URL: Homepage, https://github.com/eddiethedean/mock-spark
Project-URL: Repository, https://github.com/eddiethedean/mock-spark
Project-URL: Issues, https://github.com/eddiethedean/mock-spark/issues
Keywords: spark,pyspark,mock,testing,development,data-engineering,dataframe,spark-session,unit-testing,type-safe,mypy,error-simulation,performance-testing,data-generation,enterprise
Classifier: Development Status :: 5 - Production/Stable
Classifier: Intended Audience :: Developers
Classifier: Operating System :: OS Independent
Classifier: Programming Language :: Python :: 3
Classifier: Programming Language :: Python :: 3.9
Classifier: Programming Language :: Python :: 3.10
Classifier: Programming Language :: Python :: 3.11
Classifier: Topic :: Software Development :: Testing
Classifier: Topic :: Software Development :: Libraries :: Python Modules
Classifier: Topic :: Scientific/Engineering :: Information Analysis
Requires-Python: >=3.9
License-File: LICENSE
Requires-Dist: spark-ddl-parser>=0.1.0
Requires-Dist: polars>=0.20.0
Requires-Dist: psutil>=5.8.0
Provides-Extra: analytics
Requires-Dist: pandas>=1.3.0; extra == "analytics"
Requires-Dist: pandas-stubs>=2.0.0; extra == "analytics"
Requires-Dist: numpy>=1.20.0; extra == "analytics"
Requires-Dist: polars[pyarrow]>=0.20.0; extra == "analytics"
Provides-Extra: dev
Requires-Dist: pytest>=7.0.0; extra == "dev"
Requires-Dist: pytest-cov>=4.0.0; extra == "dev"
Requires-Dist: pytest-xdist>=3.0.0; extra == "dev"
Requires-Dist: mypy>=1.19.0; extra == "dev"
Requires-Dist: ruff>=0.4.0; extra == "dev"
Requires-Dist: pandas>=1.3.0; extra == "dev"
Requires-Dist: pandas-stubs>=2.0.0; extra == "dev"
Requires-Dist: types-psutil>=6.0.0; extra == "dev"
Provides-Extra: generate-outputs
Requires-Dist: pyspark<3.6.0,>=3.2.0; extra == "generate-outputs"
Requires-Dist: delta-spark<2.2.0,>=2.0.0; extra == "generate-outputs"
Provides-Extra: pandas
Requires-Dist: pandas>=1.3.0; extra == "pandas"
Requires-Dist: pandas-stubs>=2.0.0; extra == "pandas"
Provides-Extra: test
Requires-Dist: pytest>=7.0.0; extra == "test"
Requires-Dist: pytest-cov>=4.0.0; extra == "test"
Requires-Dist: pytest-xdist>=3.0.0; extra == "test"
Requires-Dist: hypothesis>=6.0.0; extra == "test"
